grony/__init__.py
grony/cli_app.py
grony/cli_output.py
grony/client.py
grony/commands.py
grony/dotfile.py
grony/main.py
grony/scheduler.py
grony/server.py
grony-0.4.2.dist-info/LICENSE.md
grony-0.4.2.dist-info/METADATA
grony-0.4.2.dist-info/WHEEL
grony-0.4.2.dist-info/entry_points.txt
grony-0.4.2.dist-info/top_level.txt
grony-0.4.2.dist-info/RECORD
