Metadata-Version: 2.1
Name: grony
Version: 0.4.2
Summary: An utility to schedule git-related actions using crontab expressions.
Home-page: https://github.com/luismedel/grony
Author: Luis Medel
Author-email: luis@luismedel.com
Keywords: git,automation,cron,crontab
Classifier: Development Status :: 4 - Beta
Classifier: Environment :: Console
Classifier: Intended Audience :: Developers
Classifier: Operating System :: Unix
Classifier: Topic :: Software Development :: Version Control
Classifier: Topic :: Software Development :: Version Control :: Git
Classifier: Programming Language :: Python :: 3
Classifier: License :: OSI Approved :: GNU Affero General Public License v3 or later (AGPLv3+)
License-File: LICENSE.md
Requires-Dist: click
Requires-Dist: tabulate
Requires-Dist: crontab
